pyeact/__init__.py
pyeact/cssgen.py
pyeact/htmlgen.py
pyeact/logger_formmater.py
pyeact/server.py
pyeact-0.2.1.1.dist-info/METADATA
pyeact-0.2.1.1.dist-info/WHEEL
pyeact-0.2.1.1.dist-info/top_level.txt
pyeact-0.2.1.1.dist-info/RECORD
